{
  "_comment": "図書館カレンダー データファイル。毎年の特別休館日・祝日・図書館一覧を管理します。",
  "FY2025": {
    "central": {
      "special_closed": [
        "2025-09-25",
        "2025-09-26",
        "2025-09-27",
        "2025-09-28",
        "2025-09-29",
        "2025-09-30",
        "2026-01-04",
        "2026-01-21"
      ]
    },
    "yamanaka": {
      "special_closed": [
        "2025-09-02",
        "2025-09-03",
        "2025-09-04",
        "2025-09-05",
        "2025-09-06",
        "2025-09-07",
        "2025-09-08",
        "2025-09-09",
        "2026-01-04",
        "2026-01-21",
        "2026-02-18",
        "2025-05-21",
        "2025-06-18",
        "2025-07-16"
      ]
    },
    "neagari": {
      "special_closed": [
        "2026-03-14",
        "2026-03-15"
      ],
      "special_open": [
        "2026-03-13"
      ]
    },
    "harue": {
      "special_closed": [
        "2026-03-21"
      ]
    },
    "fukui_pref": {},
    "awara": {
      "special_closed": [
        "2026-02-24",
        "2026-02-25",
        "2026-02-26",
        "2026-02-27"
      ]
    },
    "ishikawa_pref": {}
  },
  "FY2026": {
    "central": {
      "special_closed": [
        "2027-01-05",
        "2027-02-04",
        "2027-02-05",
        "2027-02-06",
        "2027-02-07",
        "2027-02-08",
        "2027-02-09",
        "2027-02-10",
        "2027-02-11",
        "2027-02-12",
        "2027-02-13",
        "2027-02-14",
        "2027-02-15",
        "2027-02-16"
      ],
      "third_tues": [
        "2026-05-19",
        "2026-06-16",
        "2026-07-14",
        "2026-10-20",
        "2026-12-15"
      ],
      "special_open": [
        "2026-05-19"
      ]
    },
    "yamanaka": {
      "special_closed": [
        "2027-01-04",
        "2027-01-26",
        "2027-01-27",
        "2027-01-28",
        "2027-01-29",
        "2027-01-30",
        "2027-01-31",
        "2027-02-01",
        "2027-02-02"
      ],
      "third_tues": [
        "2026-05-19",
        "2026-06-16",
        "2026-07-14",
        "2026-10-20",
        "2026-12-15"
      ]
    },
    "neagari": {
      "special_closed": [
        "2026-05-03",
        "2026-05-04",
        "2027-03-13",
        "2027-03-14"
      ],
      "special_open": [
        "2026-05-08"
      ]
    },
    "harue": {
      "special_closed": [
        "2026-05-14"
      ]
    },
    "fukui_pref": {
      "special_closed": [
        "2026-04-14",
        "2026-04-15",
        "2026-04-16",
        "2026-04-17"
      ],
      "special_open": [
        "2026-04-23",
        "2026-05-05",
        "2026-05-06"
      ]
    },
    "awara": {
      "special_closed": [
        "2026-05-07"
      ]
    },
    "ishikawa_pref": {
      "special_closed": [
        "2026-05-07",
        "2026-12-21",
        "2026-12-22",
        "2026-12-23",
        "2026-12-24",
        "2026-12-25",
        "2026-12-26",
        "2026-12-27",
        "2026-12-28",
        "2026-12-29",
        "2026-12-30",
        "2026-12-31",
        "2027-01-01",
        "2027-01-02",
        "2027-01-03",
        "2027-01-04",
        "2027-01-05",
        "2027-01-06",
        "2027-01-07",
        "2027-01-08",
        "2027-01-09",
        "2027-01-10",
        "2027-01-11",
        "2027-01-12",
        "2027-01-13",
        "2027-01-14",
        "2027-01-15",
        "2027-01-16",
        "2027-01-17",
        "2027-01-18",
        "2027-01-19",
        "2027-01-20",
        "2027-01-21",
        "2027-01-22",
        "2027-01-23",
        "2027-01-24"
      ]
    }
  },
  "libraries": [
    {
      "name": "中央図書館 (加賀)",
      "id": "central",
      "url": "https://www.kagalib.jp/00_calendar/calendar.pdf",
      "hours": {
        "weekday": "9:00 - 19:00",
        "weekend": "9:00 - 18:00"
      },
      "rules": {
        "weekly_closed": [
          1
        ],
        "holiday_open": true,
        "new_year_closed": [
          "12-29",
          "12-30",
          "12-31",
          "01-01",
          "01-02",
          "01-03"
        ]
      }
    },
    {
      "name": "山中図書館 (加賀)",
      "id": "yamanaka",
      "url": "https://www.kagalib.jp/00_calendar/calendar.pdf",
      "hours": {
        "weekday": "9:00 - 18:00",
        "weekend": "9:00 - 18:00"
      },
      "rules": {
        "weekly_closed": [
          5
        ],
        "holiday_open": true,
        "new_year_closed": [
          "12-29",
          "12-30",
          "12-31",
          "01-01",
          "01-02",
          "01-03"
        ]
      }
    },
    {
      "name": "根上図書館 (能美)",
      "id": "neagari",
      "url": "https://www.city.nomi.ishikawa.jp/www/genre/1000100000285/index.html",
      "hours": {
        "weekday": "9:30 - 19:00",
        "weekend": "9:30 - 17:00"
      },
      "rules": {
        "weekly_closed": [
          2
        ],
        "nth_friday": 2,
        "holiday_open": false,
        "new_year_closed": [
          "12-29",
          "12-30",
          "12-31",
          "01-01",
          "01-02",
          "01-03"
        ]
      }
    },
    {
      "name": "春江図書館 (坂井)",
      "id": "harue",
      "url": "https://lib.city.sakai.fukui.jp/",
      "hours": {
        "weekday": "9:30 - 18:30",
        "weekend": "9:30 - 18:30"
      },
      "rules": {
        "weekly_closed": [
          1
        ],
        "nth_thu": 1,
        "holiday_shift": true,
        "new_year_closed": [
          "12-29",
          "12-30",
          "12-31",
          "01-01",
          "01-02",
          "01-03",
          "01-04"
        ]
      }
    },
    {
      "name": "福井県立図書館",
      "id": "fukui_pref",
      "url": "https://www.library-archives.pref.fukui.lg.jp/tosyo/contents/calendar/index.html",
      "hours": {
        "weekday": "9:00 - 19:00",
        "weekend": "9:00 - 18:00"
      },
      "rules": {
        "weekly_closed": [
          1
        ],
        "nth_thu": 4,
        "holiday_shift": true,
        "holiday_next_day_closed": true,
        "new_year_closed": [
          "12-28",
          "12-29",
          "12-30",
          "12-31",
          "01-01",
          "01-02",
          "01-03",
          "01-04"
        ]
      }
    },
    {
      "name": "金津図書館 (あわら)",
      "id": "awara",
      "url": "https://lib.city.awara.lg.jp/",
      "hours": {
        "weekday": "9:30 - 18:00",
        "weekend": "9:30 - 18:00"
      },
      "rules": {
        "weekly_closed": [
          1
        ],
        "nth_thu": 4,
        "holiday_shift": true,
        "new_year_closed": [
          "12-29",
          "12-30",
          "12-31",
          "01-01",
          "01-02",
          "01-03"
        ]
      }
    },
    {
      "name": "石川県立図書館",
      "id": "ishikawa_pref",
      "url": "https://www.library.pref.ishikawa.lg.jp/",
      "hours": {
        "weekday": "9:00 - 19:00",
        "weekend": "9:00 - 18:00"
      },
      "rules": {
        "weekly_closed": [
          1
        ],
        "holiday_shift": true,
        "new_year_closed": [
          "12-29",
          "12-30",
          "12-31",
          "01-01",
          "01-02",
          "01-03"
        ]
      }
    }
  ],
  "holidays": [
    "2025-01-01",
    "2025-01-13",
    "2025-02-11",
    "2025-02-23",
    "2025-02-24",
    "2025-03-20",
    "2025-04-29",
    "2025-05-03",
    "2025-05-04",
    "2025-05-05",
    "2025-05-06",
    "2025-07-21",
    "2025-08-11",
    "2025-09-15",
    "2025-09-22",
    "2025-09-23",
    "2025-10-13",
    "2025-11-03",
    "2025-11-23",
    "2025-11-24",
    "2026-01-01",
    "2026-01-12",
    "2026-02-11",
    "2026-02-23",
    "2026-03-20",
    "2026-04-29",
    "2026-05-03",
    "2026-05-04",
    "2026-05-05",
    "2026-05-06",
    "2026-07-20",
    "2026-08-11",
    "2026-09-21",
    "2026-09-22",
    "2026-09-23",
    "2026-10-12",
    "2026-11-03",
    "2026-11-23",
    "2027-01-01",
    "2027-01-11",
    "2027-02-11",
    "2027-02-23"
  ]
}